clearml_darknet/__init__.py
clearml_darknet/darknet.py
clearml_darknet/errors.py
clearml_darknet/utils.py
clearml_darknet_py-0.2.1.dist-info/LICENSE
clearml_darknet_py-0.2.1.dist-info/METADATA
clearml_darknet_py-0.2.1.dist-info/WHEEL
clearml_darknet_py-0.2.1.dist-info/top_level.txt
clearml_darknet_py-0.2.1.dist-info/RECORD
