Metadata-Version: 2.1
Name: clearml-darknet-py
Version: 0.2.1
Summary: The library reproduces the reproduction of neural networks on the Darknet framework in ClearML.
Home-page: https://github.com/dkubatin/clearml-darknet-py
Author: Denis Kubatin
Author-email: kubatin.denis@gmail.com
License: MIT
Keywords: darknet,clearml,machine-learning,deep-learning,neural-network
Platform: any
Classifier: Development Status :: 5 - Production/Stable
Classifier: Intended Audience :: Science/Research
Classifier: Intended Audience :: Developers
Classifier: License :: OSI Approved :: MIT License
Classifier: Topic :: Scientific/Engineering :: Artificial Intelligence
Classifier: Topic :: Software Development
Classifier: Topic :: Software Development :: Version Control
Classifier: Topic :: System :: Logging
Classifier: Topic :: System :: Monitoring
Classifier: Programming Language :: Python :: 3.6
Classifier: Programming Language :: Python :: 3.7
Classifier: Programming Language :: Python :: 3.8
Classifier: Programming Language :: Python :: 3.9
Requires-Python: >=3.6
License-File: LICENSE
Requires-Dist: clearml (==1.4.1)
